prism/__init__.py
prism/__main__.py
prism_ai_cli-0.1.5.dist-info/METADATA
prism_ai_cli-0.1.5.dist-info/WHEEL
prism_ai_cli-0.1.5.dist-info/entry_points.txt
prism_ai_cli-0.1.5.dist-info/top_level.txt
prism_ai_cli-0.1.5.dist-info/RECORD
