Metadata-Version: 2.4
Name: prism-ai-cli
Version: 0.1.5
Summary: Prism AI CLI — Next-gen AI infrastructure
Author-email: Your Name <you@prism.ai>
License: MIT
Project-URL: Homepage, https://prism.ai
Requires-Python: >=3.8
